README.rst
setup.py
adbpy/__init__.py
adbpy/adb.py
adbpy/adb_process.py
adbpy/devices.py
adbpy/host_command.py
adbpy/socket.py
adbpy.egg-info/PKG-INFO
adbpy.egg-info/SOURCES.txt
adbpy.egg-info/dependency_links.txt
adbpy.egg-info/top_level.txt
adbpy.egg-info/zip-safe