Metadata-Version: 1.0
Name: adbpy
Version: 0.1.1
Summary: A library to communicate with ADB through it's internal socket interface, rather than the commandline.
Home-page: https://github.com/noahgoldman/adbpy
Author: Noah Goldman
Author-email: noah@phaaze.com
License: MIT
Platform: any
